wt_profile_tool/__init__.py
wt_profile_tool/_client.py
wt_profile_tool/_main.py
wt_profile_tool/decode/_profile_decoder.py
wt_profile_tool/schema/profile.py
wt_profile_tool/schema/user.py
wt_profile_tool-0.4.0.dist-info/LICENSE
wt_profile_tool-0.4.0.dist-info/METADATA
wt_profile_tool-0.4.0.dist-info/WHEEL
wt_profile_tool-0.4.0.dist-info/RECORD
