Metadata-Version: 2.1
Name: wt-profile-tool
Version: 0.4.0
Summary: wt-profile-tool contains set of tools used to fetch user profile from the WarThunder server
License: MIT
Author: axiangcoding
Author-email: axiangcoding@gmail.com
Requires-Python: >=3.11,<4.0
Classifier: License :: OSI Approved :: MIT License
Classifier: Programming Language :: Python :: 3
Classifier: Programming Language :: Python :: 3.11
Classifier: Programming Language :: Python :: 3.12
Requires-Dist: bbpb (>=1.1.0,<2.0.0)
Requires-Dist: fake-useragent (>=1.4.0,<2.0.0)
Requires-Dist: httpx (>=0.26.0,<0.27.0)
Requires-Dist: loguru (>=0.7.2,<0.8.0)
Requires-Dist: pydantic (>=2.5.3,<3.0.0)
